{
    "autopairs": {
        "cargoLocks": null,
        "date": "2023-09-08",
        "extract": null,
        "name": "autopairs",
        "passthru": null,
        "pinned": false,
        "src": {
            "deepClone": false,
            "fetchSubmodules": false,
            "leaveDotGit": false,
            "name": null,
            "rev": "defad64afbf19381fe31488a7582bbac421d6e38",
            "sha256": "sha256-N/Z+JfhJ5N8zwshpxm8bKFDbBRRQKZ9zAI+Q6mPOMBY=",
            "type": "git",
            "url": "https://github.com/windwp/nvim-autopairs"
        },
        "version": "defad64afbf19381fe31488a7582bbac421d6e38"
    },
    "bufdelete-nvim": {
        "cargoLocks": null,
        "date": "2023-06-29",
        "extract": null,
        "name": "bufdelete-nvim",
        "passthru": null,
        "pinned": false,
        "src": {
            "deepClone": false,
            "fetchSubmodules": false,
            "leaveDotGit": false,
            "name": null,
            "rev": "07d1f8ba79dec59d42b975a4df1c732b2e4e37b4",
            "sha256": "sha256-UubYRfRAXZ89WOc3QFMvAMjNjLW6bV4nDgSa1CRZkIM=",
            "type": "git",
            "url": "https://github.com/famiu/bufdelete.nvim"
        },
        "version": "07d1f8ba79dec59d42b975a4df1c732b2e4e37b4"
    },
    "bufferline-lua": {
        "cargoLocks": null,
        "date": "2023-08-29",
        "extract": null,
        "name": "bufferline-lua",
        "passthru": null,
        "pinned": false,
        "src": {
            "deepClone": false,
            "fetchSubmodules": false,
            "leaveDotGit": false,
            "name": null,
            "rev": "9961d87bb3ec008213c46ba14b3f384a5f520eb5",
            "sha256": "sha256-Wo6oAbqG0SOJ4dKjg85s/IJGe1Z6XnyjVPzQZ00Lojw=",
            "type": "git",
            "url": "https://github.com/akinsho/bufferline.nvim"
        },
        "version": "9961d87bb3ec008213c46ba14b3f384a5f520eb5"
    },
    "cinnamon": {
        "cargoLocks": null,
        "date": "2022-12-04",
        "extract": null,
        "name": "cinnamon",
        "passthru": null,
        "pinned": false,
        "src": {
            "deepClone": false,
            "fetchSubmodules": false,
            "leaveDotGit": false,
            "name": null,
            "rev": "c406ffda3a0302f32c23b24ab756ea20467d6578",
            "sha256": "sha256-JglXQhoPgN9sQ3yuv0+VQxmKMvoQTu5lbGLSRaQkytI=",
            "type": "git",
            "url": "https://github.com/declancm/cinnamon.nvim"
        },
        "version": "c406ffda3a0302f32c23b24ab756ea20467d6578"
    },
    "cmp": {
        "cargoLocks": null,
        "date": "2023-08-26",
        "extract": null,
        "name": "cmp",
        "passthru": null,
        "pinned": false,
        "src": {
            "deepClone": false,
            "fetchSubmodules": false,
            "leaveDotGit": false,
            "name": null,
            "rev": "5dce1b778b85c717f6614e3f4da45e9f19f54435",
            "sha256": "sha256-WGck3By9GhnBUmzLGi2wnKjDreQx5kBOmHCbC5BZhfo=",
            "type": "git",
            "url": "https://github.com/hrsh7th/nvim-cmp"
        },
        "version": "5dce1b778b85c717f6614e3f4da45e9f19f54435"
    },
    "cmp-buffer": {
        "cargoLocks": null,
        "date": "2022-08-10",
        "extract": null,
        "name": "cmp-buffer",
        "passthru": null,
        "pinned": false,
        "src": {
            "deepClone": false,
            "fetchSubmodules": false,
            "leaveDotGit": false,
            "name": null,
            "rev": "3022dbc9166796b644a841a02de8dd1cc1d311fa",
            "sha256": "sha256-dG4U7MtnXThoa/PD+qFtCt76MQ14V1wX8GMYcvxEnbM=",
            "type": "git",
            "url": "https://github.com/hrsh7th/cmp-buffer"
        },
        "version": "3022dbc9166796b644a841a02de8dd1cc1d311fa"
    },
    "cmp-nvim-lsp": {
        "cargoLocks": null,
        "date": "2023-06-23",
        "extract": null,
        "name": "cmp-nvim-lsp",
        "passthru": null,
        "pinned": false,
        "src": {
            "deepClone": false,
            "fetchSubmodules": false,
            "leaveDotGit": false,
            "name": null,
            "rev": "44b16d11215dce86f253ce0c30949813c0a90765",
            "sha256": "sha256-mU0soCz79erJXMMqD/FyrJZ0mu2n6fE0deymPzQlxts=",
            "type": "git",
            "url": "https://github.com/hrsh7th/cmp-nvim-lsp"
        },
        "version": "44b16d11215dce86f253ce0c30949813c0a90765"
    },
    "cmp-path": {
        "cargoLocks": null,
        "date": "2022-10-03",
        "extract": null,
        "name": "cmp-path",
        "passthru": null,
        "pinned": false,
        "src": {
            "deepClone": false,
            "fetchSubmodules": false,
            "leaveDotGit": false,
            "name": null,
            "rev": "91ff86cd9c29299a64f968ebb45846c485725f23",
            "sha256": "sha256-thppiiV3wjIaZnAXmsh7j3DUc6ceSCvGzviwFUnoPaI=",
            "type": "git",
            "url": "https://github.com/hrsh7th/cmp-path"
        },
        "version": "91ff86cd9c29299a64f968ebb45846c485725f23"
    },
    "cmp-spell": {
        "cargoLocks": null,
        "date": "2022-10-10",
        "extract": null,
        "name": "cmp-spell",
        "passthru": null,
        "pinned": false,
        "src": {
            "deepClone": false,
            "fetchSubmodules": false,
            "leaveDotGit": false,
            "name": null,
            "rev": "60584cb75e5e8bba5a0c9e4c3ab0791e0698bffa",
            "sha256": "sha256-e6nHT+5xEXDFkWes89R85FdriPSP0fPiuoXwgBdH+9M=",
            "type": "git",
            "url": "https://github.com/f3fora/cmp-spell"
        },
        "version": "60584cb75e5e8bba5a0c9e4c3ab0791e0698bffa"
    },
    "cmp-treesitter": {
        "cargoLocks": null,
        "date": "2023-04-06",
        "extract": null,
        "name": "cmp-treesitter",
        "passthru": null,
        "pinned": false,
        "src": {
            "deepClone": false,
            "fetchSubmodules": false,
            "leaveDotGit": false,
            "name": null,
            "rev": "389eadd48c27aa6dc0e6b992644704f026802a2e",
            "sha256": "sha256-WOcg6w4M20gpMCZjZ3DpPIA55SGLjV75fhckefiVfU0=",
            "type": "git",
            "url": "https://github.com/ray-x/cmp-treesitter"
        },
        "version": "389eadd48c27aa6dc0e6b992644704f026802a2e"
    },
    "cmp-vsnip": {
        "cargoLocks": null,
        "date": "2022-11-22",
        "extract": null,
        "name": "cmp-vsnip",
        "passthru": null,
        "pinned": false,
        "src": {
            "deepClone": false,
            "fetchSubmodules": false,
            "leaveDotGit": false,
            "name": null,
            "rev": "989a8a73c44e926199bfd05fa7a516d51f2d2752",
            "sha256": "sha256-2mkN03noOr5vBvRbSb35xZKorSH+8savQNZtgM9+QcM=",
            "type": "git",
            "url": "https://github.com/hrsh7th/cmp-vsnip"
        },
        "version": "989a8a73c44e926199bfd05fa7a516d51f2d2752"
    },
    "crates": {
        "cargoLocks": null,
        "date": "2023-09-11",
        "extract": null,
        "name": "crates",
        "passthru": null,
        "pinned": false,
        "src": {
            "deepClone": false,
            "fetchSubmodules": false,
            "leaveDotGit": false,
            "name": null,
            "rev": "db629b5cfb2aa8de9e44efb795657297ee95ca91",
            "sha256": "sha256-zBp7hOLJUsZ889qHZZSDSu5txO40kCexJgSAA5R7zQI=",
            "type": "git",
            "url": "https://github.com/saecki/crates.nvim"
        },
        "version": "db629b5cfb2aa8de9e44efb795657297ee95ca91"
    },
    "gitsigns": {
        "cargoLocks": null,
        "date": "2023-09-12",
        "extract": null,
        "name": "gitsigns",
        "passthru": null,
        "pinned": false,
        "src": {
            "deepClone": false,
            "fetchSubmodules": false,
            "leaveDotGit": false,
            "name": null,
            "rev": "907ae8636016aab2f283576fc60d46ca3427e579",
            "sha256": "sha256-GwCMj/R6pUIsfTLY8YKjdf2Bv/qaYcvN/S53jCGcUWw=",
            "type": "git",
            "url": "https://github.com/lewis6991/gitsigns.nvim"
        },
        "version": "907ae8636016aab2f283576fc60d46ca3427e579"
    },
    "indent-blankline": {
        "cargoLocks": null,
        "date": "2023-08-22",
        "extract": null,
        "name": "indent-blankline",
        "passthru": null,
        "pinned": false,
        "src": {
            "deepClone": false,
            "fetchSubmodules": false,
            "leaveDotGit": false,
            "name": null,
            "rev": "9637670896b68805430e2f72cf5d16be5b97a22a",
            "sha256": "sha256-1EpjFIJ5GK9NXS6dTMJ71w/AtLtR6Q5HrAXCIRNOBAY=",
            "type": "git",
            "url": "https://github.com/lukas-reineke/indent-blankline.nvim"
        },
        "version": "9637670896b68805430e2f72cf5d16be5b97a22a"
    },
    "lspkind": {
        "cargoLocks": null,
        "date": "2023-05-05",
        "extract": null,
        "name": "lspkind",
        "passthru": null,
        "pinned": false,
        "src": {
            "deepClone": false,
            "fetchSubmodules": false,
            "leaveDotGit": false,
            "name": null,
            "rev": "57610d5ab560c073c465d6faf0c19f200cb67e6e",
            "sha256": "sha256-S+qZm51hw/cRujIfHV/1x1fYyCKI4XQ0utSL8uy4l6I=",
            "type": "git",
            "url": "https://github.com/onsails/lspkind.nvim"
        },
        "version": "57610d5ab560c073c465d6faf0c19f200cb67e6e"
    },
    "lualine": {
        "cargoLocks": null,
        "date": "2023-08-03",
        "extract": null,
        "name": "lualine",
        "passthru": null,
        "pinned": false,
        "src": {
            "deepClone": false,
            "fetchSubmodules": false,
            "leaveDotGit": false,
            "name": null,
            "rev": "45e27ca739c7be6c49e5496d14fcf45a303c3a63",
            "sha256": "sha256-v8finXk+sLNaFMA7pSHhEu0WF5mhPYWHEKhl0IKBv8c=",
            "type": "git",
            "url": "https://github.com/nvim-lualine/lualine.nvim"
        },
        "version": "45e27ca739c7be6c49e5496d14fcf45a303c3a63"
    },
    "moonfly": {
        "cargoLocks": null,
        "date": "2023-09-01",
        "extract": null,
        "name": "moonfly",
        "passthru": null,
        "pinned": false,
        "src": {
            "deepClone": false,
            "fetchSubmodules": false,
            "leaveDotGit": false,
            "name": null,
            "rev": "1e81cbb88a34c41572fde43cd633bd6d60727274",
            "sha256": "sha256-omIrRr9zXC5K45TgInGoQmA4EIEGWvWIuJWRfcMfh2k=",
            "type": "git",
            "url": "https://github.com/bluz71/vim-moonfly-colors"
        },
        "version": "1e81cbb88a34c41572fde43cd633bd6d60727274"
    },
    "noice": {
        "cargoLocks": null,
        "date": "2023-08-30",
        "extract": null,
        "name": "noice",
        "passthru": null,
        "pinned": false,
        "src": {
            "deepClone": false,
            "fetchSubmodules": false,
            "leaveDotGit": false,
            "name": null,
            "rev": "74c2902146b080035beb19944baf6f014a954720",
            "sha256": "sha256-TDAmbqlUjoa2uB9LZRXDhPOZPi62MXpOXKFnaHfPUoM=",
            "type": "git",
            "url": "https://github.com/folke/noice.nvim"
        },
        "version": "74c2902146b080035beb19944baf6f014a954720"
    },
    "nui": {
        "cargoLocks": null,
        "date": "2023-09-06",
        "extract": null,
        "name": "nui",
        "passthru": null,
        "pinned": false,
        "src": {
            "deepClone": false,
            "fetchSubmodules": false,
            "leaveDotGit": false,
            "name": null,
            "rev": "c8de23342caf8d50b15d6b28368d36a56a69d76f",
            "sha256": "sha256-Ao+xnowsZPR9x3Wm439l1QIlgt3Rt6n9DZIqkUKsR1k=",
            "type": "git",
            "url": "https://github.com/MunifTanjim/nui.nvim"
        },
        "version": "c8de23342caf8d50b15d6b28368d36a56a69d76f"
    },
    "null-ls": {
        "cargoLocks": null,
        "date": "2023-08-11",
        "extract": null,
        "name": "null-ls",
        "passthru": null,
        "pinned": false,
        "src": {
            "deepClone": false,
            "fetchSubmodules": false,
            "leaveDotGit": false,
            "name": null,
            "rev": "0010ea927ab7c09ef0ce9bf28c2b573fc302f5a7",
            "sha256": "sha256-cWA0rzkOp/ekVKaFee7iea1lhnqKtWUIU+fW5M950wI=",
            "type": "git",
            "url": "https://github.com/jose-elias-alvarez/null-ls.nvim"
        },
        "version": "0010ea927ab7c09ef0ce9bf28c2b573fc302f5a7"
    },
    "nvim-colorzier": {
        "cargoLocks": null,
        "date": "2020-06-11",
        "extract": null,
        "name": "nvim-colorzier",
        "passthru": null,
        "pinned": false,
        "src": {
            "deepClone": false,
            "fetchSubmodules": false,
            "leaveDotGit": false,
            "name": null,
            "rev": "36c610a9717cc9ec426a07c8e6bf3b3abcb139d6",
            "sha256": "sha256-6YrnItxExL2C8pNIdLd+hXCjsB2MbZANwWkah6dreD8=",
            "type": "git",
            "url": "https://github.com/norcalli/nvim-colorizer.lua"
        },
        "version": "36c610a9717cc9ec426a07c8e6bf3b3abcb139d6"
    },
    "nvim-lspconfig": {
        "cargoLocks": null,
        "date": "2023-09-15",
        "extract": null,
        "name": "nvim-lspconfig",
        "passthru": null,
        "pinned": false,
        "src": {
            "deepClone": false,
            "fetchSubmodules": false,
            "leaveDotGit": false,
            "name": null,
            "rev": "cc388d3f6b9c7c943ae2b2dcd46ad470fd257f91",
            "sha256": "sha256-uofhYbag09GSUyehP1gYU4nn3ZniZXC/EnrikZTvgXc=",
            "type": "git",
            "url": "https://github.com/neovim/nvim-lspconfig"
        },
        "version": "cc388d3f6b9c7c943ae2b2dcd46ad470fd257f91"
    },
    "plenary": {
        "cargoLocks": null,
        "date": "2023-09-12",
        "extract": null,
        "name": "plenary",
        "passthru": null,
        "pinned": false,
        "src": {
            "deepClone": false,
            "fetchSubmodules": false,
            "leaveDotGit": false,
            "name": null,
            "rev": "9ce85b0f7dcfe5358c0be937ad23e456907d410b",
            "sha256": "sha256-s3qsKf05X5W1VdZT1vYXGQNK0UaiI+umWUf06Spe4hw=",
            "type": "git",
            "url": "https://github.com/nvim-lua/plenary.nvim"
        },
        "version": "9ce85b0f7dcfe5358c0be937ad23e456907d410b"
    },
    "rust-tools": {
        "cargoLocks": null,
        "date": "2023-07-10",
        "extract": null,
        "name": "rust-tools",
        "passthru": null,
        "pinned": false,
        "src": {
            "deepClone": false,
            "fetchSubmodules": false,
            "leaveDotGit": false,
            "name": null,
            "rev": "0cc8adab23117783a0292a0c8a2fbed1005dc645",
            "sha256": "sha256-jtfyDxifchznUupLSao6nmpVqaX1yO0xN+NhqS9fgxg=",
            "type": "git",
            "url": "https://github.com/simrat39/rust-tools.nvim"
        },
        "version": "0cc8adab23117783a0292a0c8a2fbed1005dc645"
    },
    "telescope": {
        "cargoLocks": null,
        "date": "2023-09-14",
        "extract": null,
        "name": "telescope",
        "passthru": null,
        "pinned": false,
        "src": {
            "deepClone": false,
            "fetchSubmodules": false,
            "leaveDotGit": false,
            "name": null,
            "rev": "59812c26d826e8c717e29406267ea1260f71e103",
            "sha256": "sha256-inOMYWkjViHzH8N3GquhN9y1z/wOm5cSblVLdcnRr7A=",
            "type": "git",
            "url": "https://github.com/nvim-telescope/telescope.nvim"
        },
        "version": "59812c26d826e8c717e29406267ea1260f71e103"
    },
    "toggle-term": {
        "cargoLocks": null,
        "date": "2023-09-11",
        "extract": null,
        "name": "toggle-term",
        "passthru": null,
        "pinned": false,
        "src": {
            "deepClone": false,
            "fetchSubmodules": false,
            "leaveDotGit": false,
            "name": null,
            "rev": "0427b908ebefcb3701c7f2cfbdafa37d11afe71a",
            "sha256": "sha256-oOKKYbmCPlnCmO5DGHKz4JytzuFjvurRRLVPMArlufM=",
            "type": "git",
            "url": "https://github.com/akinsho/toggleterm.nvim"
        },
        "version": "0427b908ebefcb3701c7f2cfbdafa37d11afe71a"
    },
    "tree-lua": {
        "cargoLocks": null,
        "date": "2023-09-10",
        "extract": null,
        "name": "tree-lua",
        "passthru": null,
        "pinned": false,
        "src": {
            "deepClone": false,
            "fetchSubmodules": false,
            "leaveDotGit": false,
            "name": null,
            "rev": "94c7c810af205c0f00c8f105dcf490c8eb17658a",
            "sha256": "sha256-Rv3DdlqRppEum09N4cKRlj0xdPbf5QLYHzYDuxb55w8=",
            "type": "git",
            "url": "https://github.com/nvim-tree/nvim-tree.lua"
        },
        "version": "94c7c810af205c0f00c8f105dcf490c8eb17658a"
    },
    "treesitter-context": {
        "cargoLocks": null,
        "date": "2023-09-06",
        "extract": null,
        "name": "treesitter-context",
        "passthru": null,
        "pinned": false,
        "src": {
            "deepClone": false,
            "fetchSubmodules": false,
            "leaveDotGit": false,
            "name": null,
            "rev": "b6c763db8cc486215ba96e0a67418848a710ab25",
            "sha256": "sha256-K5Son2U0HI/hoH1OPV959jxK3jANkeWSygPeppjNXH0=",
            "type": "git",
            "url": "https://github.com/nvim-treesitter/nvim-treesitter-context"
        },
        "version": "b6c763db8cc486215ba96e0a67418848a710ab25"
    },
    "vsnip": {
        "cargoLocks": null,
        "date": "2023-09-15",
        "extract": null,
        "name": "vsnip",
        "passthru": null,
        "pinned": false,
        "src": {
            "deepClone": false,
            "fetchSubmodules": false,
            "leaveDotGit": false,
            "name": null,
            "rev": "be277461265f1e5c7db470aa479f30956597ea9e",
            "sha256": "sha256-EbOawtNqAxCHIclKaHfkRWlvHOKAO1p0FYpqlvH5ODo=",
            "type": "git",
            "url": "https://github.com/hrsh7th/vim-vsnip"
        },
        "version": "be277461265f1e5c7db470aa479f30956597ea9e"
    },
    "web-devicons": {
        "cargoLocks": null,
        "date": "2023-09-15",
        "extract": null,
        "name": "web-devicons",
        "passthru": null,
        "pinned": false,
        "src": {
            "deepClone": false,
            "fetchSubmodules": false,
            "leaveDotGit": false,
            "name": null,
            "rev": "973ab742f143a796a779af4d786ec409116a0d87",
            "sha256": "sha256-9IPEts+RaM7Xh1ZOS8V/rECyreHK6FRKca52n031u7o=",
            "type": "git",
            "url": "https://github.com/nvim-tree/nvim-web-devicons"
        },
        "version": "973ab742f143a796a779af4d786ec409116a0d87"
    },
    "which-key": {
        "cargoLocks": null,
        "date": "2023-07-28",
        "extract": null,
        "name": "which-key",
        "passthru": null,
        "pinned": false,
        "src": {
            "deepClone": false,
            "fetchSubmodules": false,
            "leaveDotGit": false,
            "name": null,
            "rev": "7ccf476ebe0445a741b64e36c78a682c1c6118b7",
            "sha256": "sha256-B1+EHd2eH/EbD5Kip9PfhdPyyGfIkD6rsx0Z3rXvb5w=",
            "type": "git",
            "url": "https://github.com/folke/which-key.nvim"
        },
        "version": "7ccf476ebe0445a741b64e36c78a682c1c6118b7"
    }
}